Metadata-Version: 1.1
Name: sqt
Version: 0.8.0
Summary: Command-line tools for the analysis of high-throughput sequencing data
Home-page: https://bitbucket.org/marcelm/sqt
Author: Marcel Martin
Author-email: marcel.martin@scilifelab.se
License: MIT
Platform: UNKNOWN
Classifier: Development Status :: 4 - Beta
Classifier: Environment :: Console
Classifier: Intended Audience :: Science/Research
Classifier: License :: OSI Approved :: MIT License
Classifier: Natural Language :: English
Classifier: Programming Language :: Python :: 3
Classifier: Topic :: Scientific/Engineering :: Bio-Informatics
